validated_llm/__init__.py
validated_llm/async_validation_loop.py
validated_llm/async_validator.py
validated_llm/base_validator.py
validated_llm/cached_validator.py
validated_llm/cli_config.py
validated_llm/code_formats.py
validated_llm/config.py
validated_llm/enhanced_validation.py
validated_llm/error_formatting.py
validated_llm/llm_providers/__init__.py
validated_llm/llm_providers/base.py
validated_llm/llm_providers/ollama_provider.py
validated_llm/llm_providers/openai_provider.py
validated_llm/plugins/__init__.py
validated_llm/plugins/cli.py
validated_llm/plugins/discovery.py
validated_llm/plugins/exceptions.py
validated_llm/plugins/manager.py
validated_llm/plugins/registry.py
validated_llm/py.typed
validated_llm/tasks/__init__.py
validated_llm/tasks/base_task.py
validated_llm/tasks/code_generation.py
validated_llm/tasks/code_refactoring.py
validated_llm/tasks/csv_generation.py
validated_llm/tasks/documentation.py
validated_llm/tasks/json_generation.py
validated_llm/tasks/prompt_to_task_generated/__init__.py
validated_llm/tasks/prompt_to_task_generated/email_task.py
validated_llm/tasks/prompt_to_task_generated/make_json_task.py
validated_llm/tasks/prompt_to_task_generated/story_task.py
validated_llm/tasks/software_engineering.py
validated_llm/tasks/story_to_scenes.py
validated_llm/tasks/test_generation.py
validated_llm/validation_cache.py
validated_llm/validation_loop.py
validated_llm/validators/__init__.py
validated_llm/validators/async_json_schema.py
validated_llm/validators/async_range.py
validated_llm/validators/composite.py
validated_llm/validators/config.py
validated_llm/validators/date_time.py
validated_llm/validators/documentation.py
validated_llm/validators/email.py
validated_llm/validators/enhanced_json_schema.py
validated_llm/validators/enhanced_range.py
validated_llm/validators/json_schema.py
validated_llm/validators/markdown.py
validated_llm/validators/phone_number.py
validated_llm/validators/range.py
validated_llm/validators/refactoring.py
validated_llm-0.1.18.dist-info/LICENSE
validated_llm-0.1.18.dist-info/METADATA
validated_llm-0.1.18.dist-info/WHEEL
validated_llm-0.1.18.dist-info/entry_points.txt
validated_llm-0.1.18.dist-info/RECORD
