Metadata-Version: 2.3
Name: validated-llm
Version: 0.1.18
Summary: LLM output validation with retry loops - ensure your language model responses meet requirements
License: MIT
Keywords: llm,validation,ai,language-model,retry-loop,self-correcting,reliability,openai,anthropic,ollama
Author: validated-llm contributors
Requires-Python: >=3.11,<4.0
Classifier: Development Status :: 3 - Alpha
Classifier: Intended Audience :: Developers
Classifier: License :: OSI Approved :: MIT License
Classifier: Programming Language :: Python :: 3
Classifier: Programming Language :: Python :: 3.11
Classifier: Programming Language :: Python :: 3.12
Classifier: Programming Language :: Python :: 3.13
Classifier: Programming Language :: Python :: 3.10
Classifier: Programming Language :: Python :: 3.9
Classifier: Topic :: Scientific/Engineering :: Artificial Intelligence
Classifier: Topic :: Software Development :: Libraries :: Python Modules
Requires-Dist: jsonschema (>=4.0.0,<5.0.0)
Requires-Dist: openai (>=1.0.0,<2.0.0)
Requires-Dist: pydantic (>=2.0.0,<3.0.0)
Requires-Dist: pyyaml (>=6.0,<7.0)
Requires-Dist: typing-extensions (>=4.0.0,<5.0.0)
Project-URL: Documentation, https://github.com/byte-pipe/validated-llm/blob/main/README.md
Project-URL: Homepage, https://github.com/byte-pipe/validated-llm
Project-URL: Repository, https://github.com/byte-pipe/validated-llm
